LICENSE
MANIFEST.in
README.md
requirements.txt
setup.cfg
setup.py
tests/test_unit.py
wxkit/__init__.py
wxkit.egg-info/PKG-INFO
wxkit.egg-info/SOURCES.txt
wxkit.egg-info/dependency_links.txt
wxkit.egg-info/not-zip-safe
wxkit.egg-info/requires.txt
wxkit.egg-info/top_level.txt
wxkit/models/__init__.py
wxkit/services/__init__.py
wxkit/services/accuweather.py
wxkit/services/openweather.py
wxkit/services/windy.py
wxkit/utils/__init__.py
wxkit/utils/convertor.py
wxkit/utils/httplib.py
wxkit/utils/logger.py
wxkit/utils/mathlibs.py