Metadata-Version: 1.2
Name: wxkit
Version: 1.0.12
Summary: A python library for collecting weather data and exposing API.
Home-page: https://github.com/returnchung/wxkit
Author: JuiTeng Chung
Author-email: return1225@gmail.com
License: MIT License
